_toori.cp37-win_amd64.pyd
toori/console.py
toori/main.cpp
toori/main.py
toori-1.1.4.data/data/WinDivert.dll
toori-1.1.4.data/data/WinDivert.lib
toori-1.1.4.data/data/WinDivert64.sys
toori-1.1.4.data/data/windivert.h
toori-1.1.4.dist-info/METADATA
toori-1.1.4.dist-info/WHEEL
toori-1.1.4.dist-info/entry_points.txt
toori-1.1.4.dist-info/top_level.txt
toori-1.1.4.dist-info/RECORD
