Metadata-Version: 2.1
Name: toori
Version: 1.1.4
Summary: A minimal layer 3 tunnel over http(s).
Home-page: https://github.com/kokseen1/toori
License: UNKNOWN
Platform: UNKNOWN
Requires-Python: >=3.7
Requires-Dist: python-socketio
Requires-Dist: aiohttp
